{
  "uuid": "92c35252-0dc4-4b0f-983f-ea26e7bf62d0",
  "header": "ozempikinis, -ė (būdv.)",
  "publishedDate": 1756062919085,
  "details": {
    "Bendroji informacija": {
      "Kirčiuotė": "nenustatyta",
      "Rūšis": "naujai skolintos šaknies žodis",
      "Žodžio klasė": "darinys [hibridas]",
      "Kalbos dalis": "būdvardis",
      "Kilmė": "anglų, lietuvių k. ozempikas < anglų k. ozempic.",
      "Ypatingieji požymiai": "vartosenoje itin retas",
      "Giminiški naujažodžiai": "ozempikas; ozempikinis, -ė (dktv.)",
      "Pateikta": "2025-08-24"
    },
    "Reikšmė ir vartosena": {
      "Apibrėžtis": "būdingas tiems, kurie vartoja ozempiką (apie odos būklę).",
      "Vartojimo sritys": "medicina (sveikata)",
      "Funkciniai atspalviai": "laisvasis stilius",
      "Sąsajos": "ozempikas",
      "Vartosenos pavyzdžiai": {
        "Pavyzdys": "Ar teko girdėti sąvoką “ozempikinis veidas arba kūnas”? Ne paslaptis, kad svorio metimas yra itin rūpima tema. Ir pastaruoju metu tenka daug skaityti apie preparato Ozempic naudojimą. Jo tiesioginė paskirtis yra diabeto gydymas. Tačiau tapo populiaru jį naudoti svorio mažinimui. To pasekoje, susiduriama su staigiu svorio kritimu. Ir dažniausiai oda nespėja su tuo tvarkytis, Veidas įgauna daugiau senėjimo požymių, kūnas taipogi atrodo suglebęs. Tokiu atveju - masažas gali tapti didele pagalba palaikant odą normalioje būsenoje, išlaikant jos estetinę būklę.",
        "Šaltinis": "facebook.com, Elena Zemskova.",
        "Šaltinio rūšis": "el. komunikacija",
        "Metai": "2024",
        "Kita metrika": "11 04.",
        "Pavyzdį pateikė": "Rita M."
      }
    }
  }
}