{
  "uuid": "341ba2d3-a271-45d7-b11b-64f7bb25200c",
  "header": "FAFO",
  "publishedDate": 1753904128375,
  "details": {
    "Bendroji informacija": {
      "Rūšis": "naujai skolinta santrumpa",
      "Kalbos dalis": "nėra",
      "Kilmė": "anglų, sleng. FAFO < „F*** Around and Find Out“ [švelnesnis vertimo variantas: „Pakvailiosi – sužinosi“].",
      "Pateikta": "2025-07-30"
    },
    "Reikšmė ir vartosena": {
      "Apibrėžtis": "griežtas vaikų auklėjimo stilius, leidžiantis vaikams patirti neigiamo savo elgesio padarinius, kaip atsvara švelniam Z kartos auklėjimo stiliui.",
      "Vartojimo sritys": "švietimas, visuomenė",
      "Vartosenos pavyzdžiai": {
        "Pavyzdys": "FAFO, trumpinys nuo „F—Around and Find Out“ (pasiaškink ir sužinok) – tai pastaruoju metu plintantis vaikų auklėjimo stilius, kuris teikia pirmenybę pasekmėms, o ne „švelniam auklėjimui“, kuris padėjo suformuoti Z kartą, rašo „The Wall Street Journal“ (WSJ). [...]WSJ rašo, kad FAFO (dažnai tariama „faf-o“) grindžiamas idėja, kad tėvai gali prašyti ir įspėti, bet jei vaikas pažeidžia taisykles, mama ir tėtis netrukdo jam patirti pasekmes. Nepasiėmei lietpalčio? Eik namo per lietų.",
        "Šaltinis": "alfa.lt",
        "Šaltinio rūšis": "internetinė žiniasklaida",
        "Metai": "2025",
        "Kita metrika": "07 30.",
        "Pavyzdį pateikė": "Rita M."
      }
    }
  }
}