{
  "uuid": "8e2cf9b6-0654-4f62-b7d0-29805586cfe7",
  "header": "bendragrupis, -ė (dktv.)",
  "publishedDate": 1744610074343,
  "details": {
    "Bendroji informacija": {
      "Kirčiuotos formos": "bendragrùpis, bendragrùpė",
      "Kirčiuotė": "2",
      "Rūšis": "naujadaras",
      "Žodžio klasė": "darinys",
      "Kalbos dalis": "daiktavardis",
      "Kilmė": "lietuvių",
      "Giminiški naujažodžiai": "grupinukė",
      "Duomenų pateikėjai": "pirmoji apie naujažodį pranešė duomenyno lankytoja (2025-04-10).",
      "Pateikta": "2025-04-14"
    },
    "Reikšmė ir vartosena": {
      "Apibrėžtis": "kas priklauso tai pačiai grupei.",
      "Vartojimo sritys": "bendroji vartosena",
      "Sąsajos": "darželiokas, -ė",
      "Vartosenos pavyzdžiai": {
        "1-as pavyzdys": {
          "Pavyzdys": "Sveiki, panasu, kad musu visu vaikuciai bus bendragrupiai Tai visgi nepakeite grupes pavadinimo ir bus Zirniukai? Nes direktore sake, kai klausiau, kad neaisku kaip vadinsis grupe, nes sios aukletojos i mokykla pernai islydejo butent Zirniukus",
          "Šaltinis": "supermama.lt",
          "Šaltinio rūšis": "el. komunikacija",
          "Metai": "2008",
          "Kita metrika": "09 02.",
          "Pavyzdį pateikė": "Rita M."
        },
        "2-as pavyzdys": {
          "Pavyzdys": "Sveiki gal tarp skaitančių yra lankančių ar planuojančių eiti į Viščiukų grupę? Mes berods ten eisime nuo rudens, būtų labai įdomu rasti bendragrupių,",
          "Šaltinis": "supermama.lt",
          "Šaltinio rūšis": "el. komunikacija",
          "Metai": "2009",
          "Kita metrika": "08 25.",
          "Pavyzdį pateikė": "Rita M."
        },
        "3-ias pavyzdys": {
          "Pavyzdys": "Kas bus, kai prieš metus darželį lankęs bendragrupis į jį nebegalės eiti dėl naujojo potvarkio, o tėvai neišgalės samdyti auklės? Nebūkime naivūs – ne visiems vaikams bus pasakojamos pasakos, kodėl jie nebegali eiti į darželį, bus ir tokių, kurie žinos, kaip iš tiesų yra. Pati būdama mama neapsidžiaugčiau, jei kuris nors iš mano vaikų jaustųsi pažemintas dėl to, kad nusprendėme nevakcinuoti.",
          "Šaltinis": "lrytas.lt",
          "Šaltinio rūšis": "internetinė žiniasklaida",
          "Metai": "2014",
          "Kita metrika": "02 24.",
          "Pavyzdį pateikė": "duomenyno lankytoja (2025-04-10)."
        },
        "4-as pavyzdys": {
          "Pavyzdys": "Dalis pradedančiųjų valstybių 2020 metais padidino GCI indeksą net iki 17 proc., kas leido 22 proc. pakilusiu BVP aplenkti bendragrupius, o Vietnamas ir Peru netgi pakilo į pažengusiųjų grupę.",
          "Šaltinis": "15min.lt",
          "Šaltinio rūšis": "internetinė žiniasklaida",
          "Metai": "2021",
          "Kita metrika": "02 24.",
          "Pavyzdį pateikė": "Rita M."
        },
        "5-as pavyzdys": {
          "Pavyzdys": "Žmona [...] studijų bendragrupė, projektuotoja, [...] vyro mokslinių ambicijų rėmėja.",
          "Šaltinis": "vikis.lt",
          "Šaltinio rūšis": "įvairi interneto informacija",
          "Metai": "2023",
          "Kita metrika": "04 11.",
          "Pavyzdį pateikė": "Rita M."
        },
        "6-as pavyzdys": {
          "Pavyzdys": "Kaži, ar įmanoma, kad kultupys i langus dauzytųsi? Nesu matęs gyvenime, ir turbūt bendragrupiai taip pat retas matė. Gal klystu?",
          "Šaltinis": "facebook.com",
          "Šaltinio rūšis": "el. komunikacija",
          "Metai": "2024",
          "Kita metrika": "liepa.",
          "Pavyzdį pateikė": "Rita M."
        }
      }
    }
  }
}