{
  "uuid": "fe4f54cc-6491-4f10-b58c-a72145ba3400",
  "header": "skenografija",
  "publishedDate": 1753173464273,
  "details": {
    "Bendroji informacija": {
      "Kirčiuotos formos": "skenogrãfija",
      "Kirčiuotė": "1",
      "Rūšis": "naujai skolintos šaknies žodis",
      "Žodžio klasė": "skolinys",
      "Kalbos dalis": "daiktavardis",
      "Kilmė": "anglų, 1 reikšmė: scanography (scannography) < scan +‎ radiography; 2 reikšmė: scanography (scannography) < scanner +‎ photography.",
      "Ypatingieji požymiai": "kontaminacinis skolinys",
      "Giminiški naujažodžiai": "skenas; skenograma; skenuoklis; skenuotė; skenuotojas, -a",
      "Pateikta": "2025-07-22"
    },
    "Reikšmė ir vartosena": {
      "Apibrėžtis": "dvimačių vaizdų gavimo metodas medicininės radiologijos srityje, naudojant kompiuterinį tomografą.",
      "Vartojimo sritys": "kompiuterija, medicina (sveikata)",
      "Sąsajos": "skenas; skenograma1; skenuoklis; skenuotė; skenuotojas, -a",
      "Vartosenos pavyzdžiai": {
        "Pavyzdys": "Skenografijos metu buvo tiriamos 10 aktorių, emociškai įsijaučiančių į vaidmenis, smegenys, kai jie patirdavo 9 skirtingas emocijas. Taip mokslininkai galėjo nustatyti aktyvias smegenų zonas, asmeniui patiriant vis kitus jausmus.",
        "Šaltinis": "15min.lt",
        "Šaltinio rūšis": "internetinė žiniasklaida",
        "Metai": "2013",
        "Kita metrika": "06 20.",
        "Pavyzdį pateikė": "Rita M."
      }
    }
  }
}