{
  "uuid": "790e6d3f-6bb3-4e75-8078-155c6ae8b815",
  "header": "pusrašytojas",
  "publishedDate": 1781072386603,
  "details": {
    "Bendroji informacija": {
      "Kirčiuotos formos": "pùsrašytojas, pùsrašytoja",
      "Kirčiuotė": "1",
      "Rūšis": "naujadaras",
      "Žodžio klasė": "darinys",
      "Kalbos dalis": "daiktavardis",
      "Kilmė": "lietuvių",
      "Giminiški naujažodžiai": "rašytnamis; rašytojauti; rašytuvas",
      "Pateikta": "2026-06-10"
    },
    "Reikšmė ir vartosena": {
      "Apibrėžtis": "nevykęs, prastas rašytojas.",
      "Pastabos vartotojams": "žodis netaisyklingos darybos, turėtų būti pusrašytojis (plg. bernas – pusbernis; kepalas – puskepalis; etatas – pusetatis).",
      "Vartojimo sritys": "literatūra",
      "Ekspresiniai atspalviai": "menkinamasis",
      "Vartosenos pavyzdžiai": {
        "Pavyzdys": "[...] į Lietuvą atvažiuodavo koks nors žinomas ten kinematografas ar rašytojas, ar pusrašytojas, ar žurnalistas.",
        "Šaltinis": "youtube.com; tinklalaidė „Ant laužo“ [59:40 min.].",
        "Šaltinio rūšis": "sakytinė laisvoji kalba",
        "Metai": "2026",
        "Kita metrika": "05 12.",
        "Naujažodį pavartojo": "Algis Ramanauskas Greitai",
        "Pavyzdį pateikė": "Agnė Aleksaitė-Davidavičienė (2026-05-18)."
      }
    }
  }
}