{
  "uuid": "2309b75e-03aa-4ebc-be08-a1c01da548dd",
  "header": "mic drop",
  "publishedDate": 1782212516717,
  "details": {
    "Bendroji informacija": {
      "Rūšis": "naujai skolinta keliažodė citata",
      "Žodžio klasė": "skolinys",
      "Kalbos dalis": "nėra",
      "Kilmė": "anglų, mic drop „mikrofonas išjungiamas“.",
      "Pateikta": "2026-06-23"
    },
    "Reikšmė ir vartosena": {
      "Apibrėžtis": "„aš baigiau“; „aš viską pasakiau“.",
      "Pastabos vartotojams": "frazė vartojama kalbos (teksto) pabaigoje kategoriškai pabrėžiant, kad viskas jau pasakyta, įrodyta, ir toliau nėra prasmės ginčytis.",
      "Vartojimo sritys": "el. komunikacija",
      "Funkciniai atspalviai": "slengas",
      "Vartosenos pavyzdžiai": {
        "1-as pavyzdys": {
          "Pavyzdys": "[...] Ir todėl stovint mėnulyje vienoje vietoje, Žemės visą laiką bus tame pačiame taške danguje.t.y.- Žemė suksis apie savo ašį, bet danguje NEJUDĖS. Vienintelis būdas \"pajudinti\" Žemę būnant ant mėnulio paviršiaus, tai judėti pačiam į kurią nors pusę. Tą ir rodo šios nuotraukos - krateris atėja, žemė \"kyla\". Mic drop.﻿",
          "Šaltinis": "facebook.com",
          "Šaltinio rūšis": "el. komunikacija",
          "Metai": "2020",
          "Kita metrika": "02 01.",
          "Pavyzdį pateikė": "Rita M."
        },
        "2-as pavyzdys": {
          "Pavyzdys": "[a<...> :] Aha tik kad saulys pasirodo respublikonas 😂😂😂[Op: ] Kuris paaukojo demokratams 15 USD. Mic drop 😁😁",
          "Šaltinis": "reddit.com",
          "Šaltinio rūšis": "el. komunikacija",
          "Metai": "2024",
          "Pavyzdį pateikė": "Rita M."
        },
        "3-ias pavyzdys": {
          "Pavyzdys": "Ramiau reaguokime į lietuvingliškus žodžius mūsų kalboje. Jie yra atspindys mūsų pasaulio. Kad mes – pasaulio dalyviai – ne tik stebėtojai iš provincijos. Būtų labai liūdna, jei būtų tik lietuviškai. Gi taip ir svajojom, kad atrodytų mūsų realybė – lietuvingliškai. mic drop",
          "Šaltinis": "facebook.com",
          "Šaltinio rūšis": "el. komunikacija",
          "Metai": "2024",
          "Kita metrika": "10 24.",
          "Naujažodį pavartojo": "Ieva Koncevičiūtė",
          "Pavyzdį pateikė": "Rita M."
        },
        "4-as pavyzdys": {
          "Pavyzdys": "aš tai šustras esu ant temos - sakykit ką tik norit. Bet šeima yra tik tarp vyro ir moters 😃 mic drop ☕😎😆 viskas... 😌 Kas trigerinasi... Jau iškart liūdna kad su tuom žmogum energetiniai laukai nesueis 🫠",
          "Šaltinis": "threads.com",
          "Šaltinio rūšis": "el. komunikacija",
          "Metai": "2026",
          "Kita metrika": "03 25.",
          "Pavyzdį pateikė": "Rita M."
        }
      }
    }
  }
}